mathtext/api_gradio.py
mathtext/constants.py
mathtext/data/annotated_data - answer_correct.csv
mathtext/data/annotated_data - intent_vs_answer.csv
mathtext/data/annotated_data - wholeset_annotated - modified.csv
mathtext/data/annotated_data - wholeset_annotated.csv
mathtext/data/bad_words.txt
mathtext/data/big.txt
mathtext/data/master_test_text2int.csv
mathtext/data/owen_results_predict_answer_or_intent.csv
mathtext/data/owen_results_predict_student_answer_correct.csv
mathtext/data/part_speech_tagging.jsonl
mathtext/data/part_speech_tagging_test_set.jsonl
mathtext/data/rori-old-buttons.txt
mathtext/data/test_cases_all.csv
mathtext/data/test_cases_all_backup.csv
mathtext/data/text2int_results.csv
mathtext/data/webster_dictionary.json
mathtext/data/webster_dictionary_keys.txt
mathtext/models/benchmark_models.py
mathtext/models/digital_ocean_storage.py
mathtext/models/encoders.py
mathtext/models/google_cloud_storage.py
mathtext/models/multilabel_intent_recognition.py
mathtext/models/object_storage_utils.py
mathtext/models/spacy_language_model.py
mathtext/models/storage.py
mathtext/predict_intent.py
mathtext/text_processing.py
mathtext/utils/checkers.py
mathtext/utils/converters.py
mathtext/utils/default_values.py
mathtext/utils/extractors.py
mathtext/utils/formatters.py
mathtext/utils/regex_tokenizers.py
mathtext/utils/regexes.py
mathtext-2.0.6.dist-info/LICENSE.md
mathtext-2.0.6.dist-info/METADATA
mathtext-2.0.6.dist-info/WHEEL
mathtext-2.0.6.dist-info/RECORD
