Metadata-Version: 2.1
Name: mathtext
Version: 2.0.6
Summary: Natural Language Understanding (text processing) for math symbols, digits, and words with a Gradio user interface and REST API.
Home-page: https://gitlab.com/tangibleai/community/mathtext
License: AGPL-3.0-or-later
Author: Greg Thompson
Author-email: greg@tangibleai.com
Requires-Python: >=3.9
Classifier: License :: OSI Approved :: GNU Affero General Public License v3 or later (AGPLv3+)
Classifier: Operating System :: OS Independent
Classifier: Programming Language :: Python :: 3
Classifier: Programming Language :: Python :: 3.9
Classifier: Programming Language :: Python :: 3.10
Classifier: Programming Language :: Python :: 3.11
Classifier: Programming Language :: Python :: 3.12
Classifier: Programming Language :: Python :: 3.7
Classifier: Programming Language :: Python :: 3.8
Requires-Dist: boto3 (>=1.28,<2.0)
Requires-Dist: editdistance (>=0.6.2,<0.7.0)
Requires-Dist: google-cloud-storage (>=2.10.0)
Requires-Dist: pandas-gbq (>=0.19.2)
Requires-Dist: python-dotenv (>=0.21)
Requires-Dist: scikit-image (>=0.20.0)
Requires-Dist: seaborn (>=0.13.0,<0.14.0)
Requires-Dist: sentence-transformers (==2.2.2)
Requires-Dist: spacy (>=3.7,<4.0)
Requires-Dist: torch (==2.0.0)
Requires-Dist: transformers (==4.37.1)
Requires-Dist: unidecode (>=1.3.6)
Project-URL: Repository, https://gitlab.com/tangibleai/community/mathtext
